{"resourceType":"CodeSystem","id":"0b2c2a2a-0ea2-4a63-96f4-cc02c7c4ea23","meta":{"versionId":"1","lastUpdated":"2024-11-05T17:09:06.790+13:00"},"text":{"status":"generated","div":"<div xmlns=\"http://www.w3.org/1999/xhtml\"><h2>Agency type code</h2><tt>https://standards.digital.health.nz/ns/agency-type-code</tt><p>Agency type code to be used in reporting to National Collection</p></div>"},"url":"https://standards.digital.health.nz/ns/agency-type-code","version":"20221115","name":"Agency_type_code","title":"Agency type code","status":"draft","date":"2022-11-15T00:00:00.000Z","publisher":"HISO","contact":[{"name":"HISO","telecom":[{"system":"email","value":"standards@health.govt.nz"}]}],"description":"Agency type code to be used in reporting to National Collection","caseSensitive":true,"valueSet":"https://nzhts.digital.health.nz/fhir/ValueSet/agency-type-code","compositional":false,"versionNeeded":true,"content":"complete","count":8,"concept":[{"code":"1","display":"District Health Board"},{"code":"2","display":"Community Trust"},{"code":"9","display":"Health Centres"},{"code":"10","display":"Private Health Group"},{"code":"11","display":"Cancer Screening Programme"},{"code":"12","display":"Other publicly funded agency"},{"code":"13","display":"Charitable trust or incorporated society"},{"code":"14","display":"Other non-governmental agency"}]}