{"resourceType":"ValueSet","id":"canshare-surgical-intent","meta":{"versionId":"1","lastUpdated":"2024-11-05T17:10:27.708+13:00"},"language":"en-x-sctlang-23162100-0210105","url":"https://nzhts.digital.health.nz/fhir/ValueSet/canshare-surgical-intent","identifier":[{"system":"http://canshare.co.nz/fhir/NamingSystem/valuesets","value":"canshare-surgical-intent"}],"version":"20241009","name":"canshare-surgical-intent","title":"NZ surgical intent","status":"active","experimental":false,"publisher":"Te Aho o Te Kahu","contact":[{"telecom":[{"system":"email","value":"info@teaho.govt.nz"}]}],"description":"The purpose of the surgical procedure.","compose":{"include":[{"system":"http://snomed.info/sct","version":"http://snomed.info/sct/21000210109","filter":[{"property":"constraint","op":"=","value":"373808002 |Curative| OR 363676003 |Palliative| OR 261004008 |Diagnostic|"}]}]},"expansion":{"identifier":"9d1ef928-bbc6-4fdc-90c9-8fa8c6323e07","timestamp":"2024-11-11T13:49:10+13:00","total":3,"offset":0,"parameter":[{"name":"version","valueUri":"http://snomed.info/sct|http://snomed.info/sct/21000210109/version/20241001"},{"name":"count","valueInteger":2147483647},{"name":"offset","valueInteger":0}],"contains":[{"system":"http://snomed.info/sct","code":"373808002","display":"Curative intent"},{"system":"http://snomed.info/sct","code":"261004008","display":"Diagnostic intent"},{"system":"http://snomed.info/sct","code":"363676003","display":"Palliative intent"}]}}