{"resourceType":"ValueSet","id":"canshare-head-neck-with-thyroid-topography","meta":{"versionId":"1","lastUpdated":"2024-11-05T17:10:53.475+13:00"},"language":"en-x-sctlang-23162100-0210105","url":"https://nzhts.digital.health.nz/fhir/ValueSet/canshare-head-neck-with-thyroid-topography","identifier":[{"system":"http://canshare.co.nz/fhir/NamingSystem/valuesets","value":"canshare-head-neck-with-thyroid-topography"}],"version":"20241030","name":"canshare-head-neck-with-thyroid-topography","title":"NZ cancer head and neck with thyroid topography","status":"active","experimental":false,"date":"2024-10-30","publisher":"Te Aho o Te Kahu","contact":[{"telecom":[{"system":"email","value":"info@teaho.govt.nz"}]}],"description":"The body location used to describe the point of origin for cancer of the head and neck and thyroid excluding skin topography and lymph nodes or an 'Other' value.","compose":{"include":[{"system":"http://snomed.info/sct","version":"http://snomed.info/sct/21000210109","filter":[{"property":"constraint","op":"=","value":"(^466671000210105 |New Zealand cancer head and neck topography reference set| OR 69748006 |Thyroid gland| OR 40867004 |Isthmus of thyroid gland| OR 40716006 |Pyramidal lobe of thyroid| OR 119281005 |Lobe of thyroid gland| OR 74964007 |Other|) MINUS 47975008 |Structure of root of tongue (body structure)|"}]},{"system":"http://canshare.co.nz/fhir/CodeSystem/snomed-unpublished","concept":[{"code":"7283002","display":"Base of tongue"}]}]},"expansion":{"identifier":"4829caba-447b-4593-bf1d-ba40d3dc6cf9","timestamp":"2024-11-11T13:50:27+13:00","total":129,"offset":0,"parameter":[{"name":"version","valueUri":"http://canshare.co.nz/fhir/CodeSystem/snomed-unpublished|1"},{"name":"version","valueUri":"http://snomed.info/sct|http://snomed.info/sct/21000210109/version/20241001"},{"name":"count","valueInteger":2147483647},{"name":"offset","valueInteger":0}],"contains":[{"system":"http://canshare.co.nz/fhir/CodeSystem/snomed-unpublished","version":"1","code":"7283002","display":"Base of tongue"},{"system":"http://snomed.info/sct","version":"http://snomed.info/sct/21000210109/version/20241001","code":"55940004","display":"Adenoidal structure"},{"system":"http://snomed.info/sct","version":"http://snomed.info/sct/21000210109/version/20241001","code":"129143008","display":"Alveolar process"},{"system":"http://snomed.info/sct","version":"http://snomed.info/sct/21000210109/version/20241001","code":"5560003","display":"Alveolar ridge mucous membrane structure"},{"system":"http://snomed.info/sct","version":"http://snomed.info/sct/21000210109/version/20241001","code":"43545006","display":"Aryepiglottic fold structure"},{"system":"http://snomed.info/sct","version":"http://snomed.info/sct/21000210109/version/20241001","code":"77578007","display":"Arytenoid cartilage structure"},{"system":"http://snomed.info/sct","version":"http://snomed.info/sct/21000210109/version/20241001","code":"91397008","display":"Bone structure of face"},{"system":"http://snomed.info/sct","version":"http://snomed.info/sct/21000210109/version/20241001","code":"91609006","display":"Bone structure of mandible"},{"system":"http://snomed.info/sct","version":"http://snomed.info/sct/21000210109/version/20241001","code":"70925003","display":"Bone structure of maxilla"},{"system":"http://snomed.info/sct","version":"http://snomed.info/sct/21000210109/version/20241001","code":"16811007","display":"Buccal mucosa"},{"system":"http://snomed.info/sct","version":"http://snomed.info/sct/21000210109/version/20241001","code":"83299001","display":"Commissure of lips"},{"system":"http://snomed.info/sct","version":"http://snomed.info/sct/21000210109/version/20241001","code":"8600008","display":"Cricoid cartilage structure"},{"system":"http://snomed.info/sct","version":"http://snomed.info/sct/21000210109/version/20241001","code":"360382006","display":"Embryonic branchial cleft"},{"system":"http://snomed.info/sct","version":"http://snomed.info/sct/21000210109/version/20241001","code":"61563008","display":"Epiglottis structure"},{"system":"http://snomed.info/sct","version":"http://snomed.info/sct/21000210109/version/20241001","code":"54215007","display":"Ethmoid sinus structure"},{"system":"http://snomed.info/sct","version":"http://snomed.info/sct/21000210109/version/20241001","code":"28347008","display":"External ear structure"},{"system":"http://snomed.info/sct","version":"http://snomed.info/sct/21000210109/version/20241001","code":"36360002","display":"Floor of mouth structure"},{"system":"http://snomed.info/sct","version":"http://snomed.info/sct/21000210109/version/20241001","code":"55060009","display":"Frontal sinus structure"},{"system":"http://snomed.info/sct","version":"http://snomed.info/sct/21000210109/version/20241001","code":"113279002","display":"Gingival structure"},{"system":"http://snomed.info/sct","version":"http://snomed.info/sct/21000210109/version/20241001","code":"1307006","display":"Glottis structure"},{"system":"http://snomed.info/sct","version":"http://snomed.info/sct/21000210109/version/20241001","code":"90228003","display":"Hard palate structure"},{"system":"http://snomed.info/sct","version":"http://snomed.info/sct/21000210109/version/20241001","code":"81502006","display":"Hypopharyngeal structure"},{"system":"http://snomed.info/sct","version":"http://snomed.info/sct/21000210109/version/20241001","code":"22945000","display":"Inner ear structure"},{"system":"http://snomed.info/sct","version":"http://snomed.info/sct/21000210109/version/20241001","code":"36847003","display":"Laryngeal cartilage structure"},{"system":"http://snomed.info/sct","version":"http://snomed.info/sct/21000210109/version/20241001","code":"4596009","display":"Laryngeal structure"},{"system":"http://snomed.info/sct","version":"http://snomed.info/sct/21000210109/version/20241001","code":"2048000","display":"Lingual tonsil structure"},{"system":"http://snomed.info/sct","version":"http://snomed.info/sct/21000210109/version/20241001","code":"48477009","display":"Lip structure"},{"system":"http://snomed.info/sct","version":"http://snomed.info/sct/21000210109/version/20241001","code":"32032005","display":"Lower lip structure"},{"system":"http://snomed.info/sct","version":"http://snomed.info/sct/21000210109/version/20241001","code":"119282003","display":"Major salivary gland structure"},{"system":"http://snomed.info/sct","version":"http://snomed.info/sct/21000210109/version/20241001","code":"110571004","display":"Mandibular vestibule"},{"system":"http://snomed.info/sct","version":"http://snomed.info/sct/21000210109/version/20241001","code":"4906008","display":"Mastoid antrum structure"},{"system":"http://snomed.info/sct","version":"http://snomed.info/sct/21000210109/version/20241001","code":"15924003","display":"Maxillary sinus structure"},{"system":"http://snomed.info/sct","version":"http://snomed.info/sct/21000210109/version/20241001","code":"110570003","display":"Maxillary vestibule"},{"system":"http://snomed.info/sct","version":"http://snomed.info/sct/21000210109/version/20241001","code":"25342003","display":"Middle ear structure"},{"system":"http://snomed.info/sct","version":"http://snomed.info/sct/21000210109/version/20241001","code":"87626005","display":"Minor salivary gland structure"},{"system":"http://snomed.info/sct","version":"http://snomed.info/sct/21000210109/version/20241001","code":"16178009","display":"Nasal cartilage structure"},{"system":"http://snomed.info/sct","version":"http://snomed.info/sct/21000210109/version/20241001","code":"279549004","display":"Nasal cavity structure"},{"system":"http://snomed.info/sct","version":"http://snomed.info/sct/21000210109/version/20241001","code":"68426009","display":"Nasal septum structure"},{"system":"http://snomed.info/sct","version":"http://snomed.info/sct/21000210109/version/20241001","code":"2095001","display":"Nasal sinus structure"},{"system":"http://snomed.info/sct","version":"http://snomed.info/sct/21000210109/version/20241001","code":"46607005","display":"Nasal turbinate structure"},{"system":"http://snomed.info/sct","version":"http://snomed.info/sct/21000210109/version/20241001","code":"71836000","display":"Nasopharyngeal structure"},{"system":"http://snomed.info/sct","version":"http://snomed.info/sct/21000210109/version/20241001","code":"278001007","display":"Nonspecific site"},{"system":"http://snomed.info/sct","version":"http://snomed.info/sct/21000210109/version/20241001","code":"74262004","display":"Oral cavity structure"},{"system":"http://snomed.info/sct","version":"http://snomed.info/sct/21000210109/version/20241001","code":"113277000","display":"Oral mucous membrane structure"},{"system":"http://snomed.info/sct","version":"http://snomed.info/sct/21000210109/version/20241001","code":"31389004","display":"Oropharyngeal structure"},{"system":"http://snomed.info/sct","version":"http://snomed.info/sct/21000210109/version/20241001","code":"74964007","display":"Other"},{"system":"http://snomed.info/sct","version":"http://snomed.info/sct/21000210109/version/20241001","code":"21294006","display":"Palatine arch structure"},{"system":"http://snomed.info/sct","version":"http://snomed.info/sct/21000210109/version/20241001","code":"75573002","display":"Palatine tonsillar structure"},{"system":"http://snomed.info/sct","version":"http://snomed.info/sct/21000210109/version/20241001","code":"45289007","display":"Parotid gland structure"},{"system":"http://snomed.info/sct","version":"http://snomed.info/sct/21000210109/version/20241001","code":"88089004","display":"Skin structure of lip"},{"system":"http://snomed.info/sct","version":"http://snomed.info/sct/21000210109/version/20241001","code":"66934001","display":"Skin structure of lower lip"},{"system":"http://snomed.info/sct","version":"http://snomed.info/sct/21000210109/version/20241001","code":"16251004","display":"Skin structure of upper lip"},{"system":"http://snomed.info/sct","version":"http://snomed.info/sct/21000210109/version/20241001","code":"49460000","display":"Soft palate structure"},{"system":"http://snomed.info/sct","version":"http://snomed.info/sct/21000210109/version/20241001","code":"24999009","display":"Sphenoid sinus structure"},{"system":"http://snomed.info/sct","version":"http://snomed.info/sct/21000210109/version/20241001","code":"38754007","display":"Structure of alveolar process of mandible"},{"system":"http://snomed.info/sct","version":"http://snomed.info/sct/21000210109/version/20241001","code":"415636008","display":"Structure of alveolar process of maxilla"},{"system":"http://snomed.info/sct","version":"http://snomed.info/sct/21000210109/version/20241001","code":"52131005","display":"Structure of anterior floor of mouth"},{"system":"http://snomed.info/sct","version":"http://snomed.info/sct/21000210109/version/20241001","code":"1797002","display":"Structure of anterior naris"},{"system":"http://snomed.info/sct","version":"http://snomed.info/sct/21000210109/version/20241001","code":"245796006","display":"Structure of anterior part of alveolar process of mandible"},{"system":"http://snomed.info/sct","version":"http://snomed.info/sct/21000210109/version/20241001","code":"67298002","display":"Structure of anterior surface of epiglottis"},{"system":"http://snomed.info/sct","version":"http://snomed.info/sct/21000210109/version/20241001","code":"82521001","display":"Structure of anterior wall of nasopharynx"},{"system":"http://snomed.info/sct","version":"http://snomed.info/sct/21000210109/version/20241001","code":"11048003","display":"Structure of body of mandible"},{"system":"http://snomed.info/sct","version":"http://snomed.info/sct/21000210109/version/20241001","code":"61344008","display":"Structure of body of tongue"},{"system":"http://snomed.info/sct","version":"http://snomed.info/sct/21000210109/version/20241001","code":"71717001","display":"Structure of choana"},{"system":"http://snomed.info/sct","version":"http://snomed.info/sct/21000210109/version/20241001","code":"72691007","display":"Structure of commissure of larynx"},{"system":"http://snomed.info/sct","version":"http://snomed.info/sct/21000210109/version/20241001","code":"67183008","display":"Structure of condyloid process of mandible"},{"system":"http://snomed.info/sct","version":"http://snomed.info/sct/21000210109/version/20241001","code":"124002","display":"Structure of coronoid process of mandible"},{"system":"http://snomed.info/sct","version":"http://snomed.info/sct/21000210109/version/20241001","code":"35779009","display":"Structure of cuneiform cartilage"},{"system":"http://snomed.info/sct","version":"http://snomed.info/sct/21000210109/version/20241001","code":"77711009","display":"Structure of dorsum of anterior tongue"},{"system":"http://snomed.info/sct","version":"http://snomed.info/sct/21000210109/version/20241001","code":"7652006","display":"Structure of frenulum labii"},{"system":"http://snomed.info/sct","version":"http://snomed.info/sct/21000210109/version/20241001","code":"34148009","display":"Structure of frenulum labii inferioris"},{"system":"http://snomed.info/sct","version":"http://snomed.info/sct/21000210109/version/20241001","code":"45825006","display":"Structure of frenulum labii superioris"},{"system":"http://snomed.info/sct","version":"http://snomed.info/sct/21000210109/version/20241001","code":"1159005","display":"Structure of frenulum linguae"},{"system":"http://snomed.info/sct","version":"http://snomed.info/sct/21000210109/version/20241001","code":"57131003","display":"Structure of gum of mandible"},{"system":"http://snomed.info/sct","version":"http://snomed.info/sct/21000210109/version/20241001","code":"23114008","display":"Structure of gum of maxilla"},{"system":"http://snomed.info/sct","version":"http://snomed.info/sct/21000210109/version/20241001","code":"774007","display":"Structure of head and/or neck"},{"system":"http://snomed.info/sct","version":"http://snomed.info/sct/21000210109/version/20241001","code":"36088004","display":"Structure of hypopharyngeal aspect of aryepiglottic fold"},{"system":"http://snomed.info/sct","version":"http://snomed.info/sct/21000210109/version/20241001","code":"466641000210100","display":"Structure of incisor and/or canine region alveolar process"},{"system":"http://snomed.info/sct","version":"http://snomed.info/sct/21000210109/version/20241001","code":"422005","display":"Structure of inferior surface of tongue"},{"system":"http://snomed.info/sct","version":"http://snomed.info/sct/21000210109/version/20241001","code":"40867004","display":"Structure of isthmus of thyroid gland"},{"system":"http://snomed.info/sct","version":"http://snomed.info/sct/21000210109/version/20241001","code":"28803009","display":"Structure of lateral floor of mouth"},{"system":"http://snomed.info/sct","version":"http://snomed.info/sct/21000210109/version/20241001","code":"41881006","display":"Structure of lateral margin of tongue"},{"system":"http://snomed.info/sct","version":"http://snomed.info/sct/21000210109/version/20241001","code":"12507007","display":"Structure of lateral pharyngeal space"},{"system":"http://snomed.info/sct","version":"http://snomed.info/sct/21000210109/version/20241001","code":"70988003","display":"Structure of lateral wall of nasopharynx"},{"system":"http://snomed.info/sct","version":"http://snomed.info/sct/21000210109/version/20241001","code":"19120004","display":"Structure of lateral wall of oropharynx"},{"system":"http://snomed.info/sct","version":"http://snomed.info/sct/21000210109/version/20241001","code":"119281005","display":"Structure of lobe of thyroid gland"},{"system":"http://snomed.info/sct","version":"http://snomed.info/sct/21000210109/version/20241001","code":"6912001","display":"Structure of lower alveolar ridge mucosa"},{"system":"http://snomed.info/sct","version":"http://snomed.info/sct/21000210109/version/20241001","code":"466621000210106","display":"Structure of molar region alveolar process"},{"system":"http://snomed.info/sct","version":"http://snomed.info/sct/21000210109/version/20241001","code":"312533001","display":"Structure of mouth and/or pharynx"},{"system":"http://snomed.info/sct","version":"http://snomed.info/sct/21000210109/version/20241001","code":"59641005","display":"Structure of mucous membrane of lip"},{"system":"http://snomed.info/sct","version":"http://snomed.info/sct/21000210109/version/20241001","code":"46353006","display":"Structure of mucous membrane of lower lip"},{"system":"http://snomed.info/sct","version":"http://snomed.info/sct/21000210109/version/20241001","code":"34508005","display":"Structure of mucous membrane of nose"},{"system":"http://snomed.info/sct","version":"http://snomed.info/sct/21000210109/version/20241001","code":"18444004","display":"Structure of mucous membrane of upper lip"},{"system":"http://snomed.info/sct","version":"http://snomed.info/sct/21000210109/version/20241001","code":"76786004","display":"Structure of nasopharyngeal surface of soft palate"},{"system":"http://snomed.info/sct","version":"http://snomed.info/sct/21000210109/version/20241001","code":"17861009","display":"Structure of pharyngeal lymphoid ring"},{"system":"http://snomed.info/sct","version":"http://snomed.info/sct/21000210109/version/20241001","code":"1849007","display":"Structure of pharyngeal recess"},{"system":"http://snomed.info/sct","version":"http://snomed.info/sct/21000210109/version/20241001","code":"91207004","display":"Structure of pharyngotympanic tube"},{"system":"http://snomed.info/sct","version":"http://snomed.info/sct/21000210109/version/20241001","code":"6217003","display":"Structure of piriform recess"},{"system":"http://snomed.info/sct","version":"http://snomed.info/sct/21000210109/version/20241001","code":"35806005","display":"Structure of postcricoid region"},{"system":"http://snomed.info/sct","version":"http://snomed.info/sct/21000210109/version/20241001","code":"28567000","display":"Structure of posterior wall of hypopharynx"},{"system":"http://snomed.info/sct","version":"http://snomed.info/sct/21000210109/version/20241001","code":"30157008","display":"Structure of posterior wall of nasopharynx"},{"system":"http://snomed.info/sct","version":"http://snomed.info/sct/21000210109/version/20241001","code":"12999009","display":"Structure of posterior wall of oropharynx"},{"system":"http://snomed.info/sct","version":"http://snomed.info/sct/21000210109/version/20241001","code":"466631000210108","display":"Structure of premolar region alveolar process"},{"system":"http://snomed.info/sct","version":"http://snomed.info/sct/21000210109/version/20241001","code":"40716006","display":"Structure of pyramidal lobe of thyroid"},{"system":"http://snomed.info/sct","version":"http://snomed.info/sct/21000210109/version/20241001","code":"23938008","display":"Structure of ramus of mandible"},{"system":"http://snomed.info/sct","version":"http://snomed.info/sct/21000210109/version/20241001","code":"85816001","display":"Structure of retromolar area of mouth"},{"system":"http://snomed.info/sct","version":"http://snomed.info/sct/21000210109/version/20241001","code":"20409001","display":"Structure of superior wall of nasopharynx"},{"system":"http://snomed.info/sct","version":"http://snomed.info/sct/21000210109/version/20241001","code":"73041003","display":"Structure of tip of tongue"},{"system":"http://snomed.info/sct","version":"http://snomed.info/sct/21000210109/version/20241001","code":"77459005","display":"Structure of upper alveolar ridge mucosa"},{"system":"http://snomed.info/sct","version":"http://snomed.info/sct/21000210109/version/20241001","code":"42275007","display":"Structure of vallecula of epiglottis"},{"system":"http://snomed.info/sct","version":"http://snomed.info/sct/21000210109/version/20241001","code":"74761005","display":"Structure of ventricular fold of larynx"},{"system":"http://snomed.info/sct","version":"http://snomed.info/sct/21000210109/version/20241001","code":"128251006","display":"Structure of vermilion border of lower lip"},{"system":"http://snomed.info/sct","version":"http://snomed.info/sct/21000210109/version/20241001","code":"128250007","display":"Structure of vermilion border of upper lip"},{"system":"http://snomed.info/sct","version":"http://snomed.info/sct/21000210109/version/20241001","code":"34810001","display":"Structure of vestibule of mouth"},{"system":"http://snomed.info/sct","version":"http://snomed.info/sct/21000210109/version/20241001","code":"23224007","display":"Structure of zygomatic process of maxilla"},{"system":"http://snomed.info/sct","version":"http://snomed.info/sct/21000210109/version/20241001","code":"119254005","display":"Subglottis structure"},{"system":"http://snomed.info/sct","version":"http://snomed.info/sct/21000210109/version/20241001","code":"88481005","display":"Sublingual gland structure"},{"system":"http://snomed.info/sct","version":"http://snomed.info/sct/21000210109/version/20241001","code":"385296007","display":"Submandibular salivary gland structure"},{"system":"http://snomed.info/sct","version":"http://snomed.info/sct/21000210109/version/20241001","code":"119255006","display":"Supraglottis structure"},{"system":"http://snomed.info/sct","version":"http://snomed.info/sct/21000210109/version/20241001","code":"60911003","display":"Temporal bone structure"},{"system":"http://snomed.info/sct","version":"http://snomed.info/sct/21000210109/version/20241001","code":"52940008","display":"Thyroid cartilage structure"},{"system":"http://snomed.info/sct","version":"http://snomed.info/sct/21000210109/version/20241001","code":"69748006","display":"Thyroid structure"},{"system":"http://snomed.info/sct","version":"http://snomed.info/sct/21000210109/version/20241001","code":"21974007","display":"Tongue structure"},{"system":"http://snomed.info/sct","version":"http://snomed.info/sct/21000210109/version/20241001","code":"32163006","display":"Tonsillar fossa structure"},{"system":"http://snomed.info/sct","version":"http://snomed.info/sct/21000210109/version/20241001","code":"44567001","display":"Tracheal structure"},{"system":"http://snomed.info/sct","version":"http://snomed.info/sct/21000210109/version/20241001","code":"11681001","display":"Upper lip structure"},{"system":"http://snomed.info/sct","version":"http://snomed.info/sct/21000210109/version/20241001","code":"58675001","display":"Upper respiratory tract structure"},{"system":"http://snomed.info/sct","version":"http://snomed.info/sct/21000210109/version/20241001","code":"26140008","display":"Uvula palatina structure"},{"system":"http://snomed.info/sct","version":"http://snomed.info/sct/21000210109/version/20241001","code":"46105003","display":"Vocal cord structure"}]}}