{"resourceType":"ValueSet","id":"canshare-rai-cll-stage","meta":{"versionId":"1","lastUpdated":"2024-11-05T17:13:33.357+13:00"},"language":"en-x-sctlang-23162100-0210105","url":"https://nzhts.digital.health.nz/fhir/ValueSet/canshare-rai-cll-stage","identifier":[{"system":"http://canshare.co.nz/fhir/NamingSystem/valuesets","value":"canshare-rai-cll-stage"}],"version":"20241009","name":"canshare-rai-cll-stage","title":"NZ cancer Rai staging for CLL stage","status":"active","experimental":false,"publisher":"Te Aho o Te Kahu","contact":[{"telecom":[{"system":"email","value":"info@teaho.govt.nz"}]}],"description":"The stage groups for chronic lymphocytic leukaemia, defined by Rai staging system.","compose":{"include":[{"system":"http://snomed.info/sct","version":"http://snomed.info/sct/21000210109","filter":[{"property":"constraint","op":"=","value":"^ 294791000210108 |New Zealand cancer Rai staging for CLL stage reference set|"}]}]},"expansion":{"identifier":"eeafeac5-3b03-40ed-8ea5-d5aac5289941","timestamp":"2024-11-11T13:46:16+13:00","total":5,"offset":0,"parameter":[{"name":"version","valueUri":"http://snomed.info/sct|http://snomed.info/sct/21000210109/version/20241001"},{"name":"count","valueInteger":2147483647},{"name":"offset","valueInteger":0}],"contains":[{"system":"http://snomed.info/sct","code":"295481000210102","display":"Rai staging for chronic lymphocytic leukaemia stage 0"},{"system":"http://snomed.info/sct","code":"295491000210100","display":"Rai staging for chronic lymphocytic leukaemia stage I"},{"system":"http://snomed.info/sct","code":"295501000210105","display":"Rai staging for chronic lymphocytic leukaemia stage II"},{"system":"http://snomed.info/sct","code":"295511000210107","display":"Rai staging for chronic lymphocytic leukaemia stage III"},{"system":"http://snomed.info/sct","code":"295521000210102","display":"Rai staging for chronic lymphocytic leukaemia stage IV"}]}}